{"name":"Arcanist Commit Message","scopeName":"source.fb-arcanist-editor","fileTypes":["commit.hg.txt","new-commit"],"patterns":[{"match":"^HG:.*$","name":"comment"},{"begin":"((?:^(Facebook|Summary|Test Plan|Title)):)","beginCaptures":{"1":{"name":"keyword.arcanist"}},"end":"(?=^(Facebook|Differential Revision|Reviewed By|Reviewers|Signature|Subscribers|Summary|Tasks|Test Plan|Title):)","patterns":[{"include":"source.gfm"}]},{"begin":"((?:^(Reviewed By|Reviewers|Subscribers)):)","beginCaptures":{"1":{"name":"keyword.arcanist"}},"end":"$","name":"source.fb-arcanist-editor.reviewers"},{"begin":"(^Tasks:)","beginCaptures":{"1":{"name":"keyword.arcanist"}},"end":"$","name":"source.fb-arcanist-editor.tasks"},{"begin":"((?:^(Differential Revision|Signature|Tags)):)","beginCaptures":{"1":{"name":"keyword.arcanist"}},"end":"$"}]}